breadcrumbs3/middleware.py
breadcrumbs3/__init__.py
breadcrumbs3/tests/urls.py
breadcrumbs3/tests/views.py
breadcrumbs3/tests/tests.py
breadcrumbs3/tests/__init__.py
breadcrumbs3/templatetags/breadcrumbs.py
breadcrumbs3/templatetags/__init__.py
django_breadcrumbs3-1.0.3.dist-info/METADATA
django_breadcrumbs3-1.0.3.dist-info/metadata.json
django_breadcrumbs3-1.0.3.dist-info/DESCRIPTION.rst
django_breadcrumbs3-1.0.3.dist-info/top_level.txt
django_breadcrumbs3-1.0.3.dist-info/WHEEL
django_breadcrumbs3-1.0.3.dist-info/RECORD
